[{"customers":[1,3],"flightId":1,"foods":["Standard","Vegetarian","Halal","Light Meal","Gourmet Menu","Chef's Special"],"fromCity":"Taiyuan Wusu","gateId":10,"occupiedSeats":[],"planeId":"B-1001","time":"周二 5月 24 21:35:53","toCity":"Beijing Capital"},{"customers":[1,5],"flightId":2,"foods":["Standard","Vegetarian","Halal","Light Meal","Gourmet Menu","Chef's Special"],"fromCity":"Taiyuan Wusu","gateId":20,"occupiedSeats":[],"planeId":"B-1001","time":"周二 5月 24 22:35:54","toCity":"Shanghai Pudong"},{"customers":[],"flightId":3,"foods":["Standard","Vegetarian","Halal","Light Meal","Gourmet Menu","Chef's Special"],"fromCity":"Taiyuan Wusu","gateId":30,"occupiedSeats":[],"planeId":"B-1002","time":"周二 5月 24 23:35:54","toCity":"Beijing Daxing"},{"customers":[6],"flightId":4,"foods":["Standard","Vegetarian","Halal","Light Meal","Gourmet Menu","Chef's Special"],"fromCity":"Taiyuan Wusu","gateId":40,"occupiedSeats":[],"planeId":"B-1002","time":"周三 5月 25 00:35:54","toCity":"Guangzhou Baiyun"},{"customers":[],"flightId":5,"foods":["Standard","Vegetarian","Halal","Light Meal","Gourmet Menu","Chef's Special"],"fromCity":"Taiyuan Wusu","gateId":50,"occupiedSeats":[],"planeId":"B-1002","time":"周三 5月 25 01:35:54","toCity":"Shanghai Hongqiao"},{"customers":[],"flightId":6,"foods":["Standard","Vegetarian","Halal","Light Meal","Gourmet Menu","Chef's Special"],"fromCity":"Taiyuan Wusu","gateId":60,"occupiedSeats":[],"planeId":"B-1002","time":"周三 5月 25 02:35:54","toCity":"Shenzhen Bao'an"},{"customers":[7],"flightId":7,"foods":["Standard","Vegetarian","Halal","Light Meal","Gourmet Menu","Chef's Special"],"fromCity":"Taiyuan Wusu","gateId":70,"occupiedSeats":[],"planeId":"B-1003","time":"周三 5月 25 03:35:54","toCity":"Macau"},{"customers":[],"flightId":8,"foods":["Standard","Vegetarian","Halal","Light Meal","Gourmet Menu","Chef's Special"],"fromCity":"Taiyuan Wusu","gateId":80,"occupiedSeats":[],"planeId":"B-1003","time":"周三 5月 25 04:35:54","toCity":"Changsha Huanghua"},{"customers":[],"flightId":9,"foods":["Standard","Vegetarian","Halal","Light Meal","Gourmet Menu","Chef's Special"],"fromCity":"Taiyuan Wusu","gateId":90,"occupiedSeats":[],"planeId":"B-1004","time":"周三 5月 25 06:35:54","toCity":"Kunming Wujiaba"},{"customers":[],"flightId":10,"foods":["Standard","Vegetarian","Halal","Light Meal","Gourmet Menu","Chef's Special"],"fromCity":"Taiyuan Wusu","gateId":100,"occupiedSeats":[],"planeId":"B-1004","time":"周三 5月 25 07:35:54","toCity":"Hangzhou Xiaoshan"},{"customers":[],"flightId":11,"foods":["Standard","Vegetarian","Halal","Light Meal","Gourmet Menu","Chef's Special"],"fromCity":"Taiyuan Wusu","gateId":110,"occupiedSeats":[],"planeId":"B-1004","time":"周三 5月 25 08:35:54","toCity":"Chongqing Jiangbei"},{"customers":[4],"flightId":12,"foods":["Standard","Vegetarian","Halal","Light Meal","Gourmet Menu","Chef's Special"],"fromCity":"Taiyuan Wusu","gateId":120,"occupiedSeats":[],"planeId":"B-1004","time":"周三 5月 25 09:35:54","toCity":"Hong Kong"},{"customers":[],"flightId":13,"foods":["Standard","Vegetarian","Halal","Light Meal","Gourmet Menu","Chef's Special"],"fromCity":"Taiyuan Wusu","gateId":130,"occupiedSeats":[],"planeId":"B-1005","time":"周三 5月 25 10:35:54","toCity":"Chengdu Shuangliu"},{"customers":[2],"flightId":14,"foods":["Standard","Vegetarian","Halal","Light Meal","Gourmet Menu","Chef's Special"],"fromCity":"Taiyuan Wusu","gateId":140,"occupiedSeats":[],"planeId":"B-1006","time":"周三 5月 25 11:35:54","toCity":"Shantou Waisha"},{"customers":[],"flightId":15,"foods":["Standard","Vegetarian","Halal","Light Meal","Gourmet Menu","Chef's Special"],"fromCity":"Taiyuan Wusu","gateId":150,"occupiedSeats":[],"planeId":"B-1006","time":"周三 5月 25 12:35:54","toCity":"Xi'an Xianyang"},{"customers":[],"flightId":16,"foods":["Standard","Vegetarian","Halal","Light Meal","Gourmet Menu","Chef's Special"],"fromCity":"Taiyuan Wusu","gateId":160,"occupiedSeats":[],"planeId":"B-1006","time":"周三 5月 25 13:35:54","toCity":"Nanjing Lukou"}]